a2y_fa.cp36-win32.pyd
a2y_fa-0.8.4.dist-info/LICENSE
a2y_fa-0.8.4.dist-info/METADATA
a2y_fa-0.8.4.dist-info/WHEEL
a2y_fa-0.8.4.dist-info/top_level.txt
a2y_fa-0.8.4.dist-info/RECORD
