Metadata-Version: 2.1
Name: a2y-fa
Version: 0.8.4
Summary: 本模块为工厂自动化提供一些工具，方便控制各种自动化设备。
Home-page: http://www.sorobust.com/a2y/fa.html
Author: Yu Han
Author-email: hanjunyu@163.com
License: Private
Platform: Windows
Platform: Linux
Classifier: Development Status :: 4 - Beta
Classifier: Intended Audience :: Developers
Classifier: License :: Free For Educational Use
Classifier: Programming Language :: Python :: 3.5
Classifier: Operating System :: Microsoft :: Windows :: Windows 10
Classifier: Operating System :: POSIX :: Linux
Requires-Dist: a2y-inst
Requires-Dist: a2y-mew
